smaxpy/__init__.py
smaxpy/errors.py
smaxpy/request.py
smaxpy/smax.py
smaxpy-0.1.0.dist-info/LICENSE
smaxpy-0.1.0.dist-info/METADATA
smaxpy-0.1.0.dist-info/WHEEL
smaxpy-0.1.0.dist-info/top_level.txt
smaxpy-0.1.0.dist-info/RECORD
